bible/__init__.py
bible/bible.py
bible/helpers.py
pybible_api-0.0.3.dist-info/LICENSE
pybible_api-0.0.3.dist-info/METADATA
pybible_api-0.0.3.dist-info/WHEEL
pybible_api-0.0.3.dist-info/top_level.txt
pybible_api-0.0.3.dist-info/RECORD
